{
 "actions": [],
 "allow_rename": 1,
 "creation": "2023-10-16 18:45:05.744563",
 "default_view": "List",
 "doctype": "DocType",
 "editable_grid": 1,
 "engine": "InnoDB",
 "field_order": [
  "alerts_tab",
  "status",
  "server",
  "cluster",
  "investigation",
  "column_break_smnd",
  "resource_type",
  "resource",
  "type",
  "subtype",
  "section_break_lazo",
  "confirmed_at",
  "column_break_ukex",
  "acknowledged_by",
  "column_break_kwec",
  "acknowledged_at",
  "column_break_hryl",
  "resolved_at",
  "section_break_heda",
  "likely_cause",
  "preliminary_investigation_section",
  "description",
  "analysis_tab",
  "no_of_down_sites",
  "no_of_down_benches",
  "column_break_vxrf",
  "no_of_total_sites",
  "no_of_total_benches",
  "section_break_qefz",
  "down_sites",
  "down_benches",
  "server_health_tab",
  "last_1_hour_overview_section",
  "app_server_column",
  "server_status",
  "server_load15",
  "server_free_space_gb",
  "server_disk_iops",
  "server_disk_throughput_mbps",
  "server_runnable_state",
  "server_oom_kills",
  "column_break_iqfx",
  "db_server_status",
  "db_server_load15",
  "db_free_space_gb",
  "db_server_disk_iops",
  "db_server_disk_throughput_mbps",
  "db_server_free_memory_mb",
  "db_server_disk_queue",
  "grafana_dashboard_section",
  "app_server_stats",
  "db_server_stats",
  "app_server_stats_html",
  "db_server_stats_html",
  "updates_tab",
  "section_break_aevb",
  "column_break_rbwa",
  "phone_call",
  "column_break_xvko",
  "sms_sent",
  "column_break_zzcp",
  "called_customer",
  "section_break_pahe",
  "updates"
 ],
 "fields": [
  {
   "fieldname": "server",
   "fieldtype": "Link",
   "in_list_view": 1,
   "in_standard_filter": 1,
   "label": "Server",
   "options": "Server"
  },
  {
   "fieldname": "cluster",
   "fieldtype": "Link",
   "label": "Cluster",
   "options": "Cluster"
  },
  {
   "fieldname": "column_break_smnd",
   "fieldtype": "Column Break",
   "read_only": 1
  },
  {
   "default": "Validating",
   "fieldname": "status",
   "fieldtype": "Select",
   "in_list_view": 1,
   "in_standard_filter": 1,
   "label": "Status",
   "options": "Validating\nConfirmed\nAcknowledged\nInvestigating\nResolved\nAuto-Resolved\nPress-Resolved"
  },
  {
   "default": "Database Down",
   "fieldname": "type",
   "fieldtype": "Select",
   "label": "Type",
   "options": "Database Down\nServer Down\nProxy Down"
  },
  {
   "default": "0",
   "fieldname": "sms_sent",
   "fieldtype": "Check",
   "label": "SMS Sent"
  },
  {
   "fieldname": "alerts_tab",
   "fieldtype": "Tab Break",
   "label": "Overview"
  },
  {
   "fieldname": "updates_tab",
   "fieldtype": "Tab Break",
   "label": "Updates"
  },
  {
   "fieldname": "acknowledged_by",
   "fieldtype": "Link",
   "label": "Acknowledged By",
   "mandatory_depends_on": "eval: doc.status==\"Acknowledged\";",
   "options": "User"
  },
  {
   "fieldname": "column_break_rbwa",
   "fieldtype": "Column Break"
  },
  {
   "fieldname": "section_break_aevb",
   "fieldtype": "Section Break"
  },
  {
   "fieldname": "updates",
   "fieldtype": "Table",
   "label": "Updates",
   "options": "Incident Updates"
  },
  {
   "fieldname": "description",
   "fieldtype": "Text Editor",
   "hidden": 1,
   "label": "Description"
  },
  {
   "default": "1",
   "fieldname": "phone_call",
   "fieldtype": "Check",
   "label": "Phone Call"
  },
  {
   "fieldname": "resource_type",
   "fieldtype": "Link",
   "label": "Resource Type",
   "options": "DocType"
  },
  {
   "fieldname": "resource",
   "fieldtype": "Dynamic Link",
   "in_list_view": 1,
   "in_standard_filter": 1,
   "label": "Resource",
   "options": "resource_type"
  },
  {
   "fieldname": "subtype",
   "fieldtype": "Select",
   "label": "Subtype",
   "options": "High CPU: user\nHigh CPU: iowait\nDisk full"
  },
  {
   "collapsible": 1,
   "fieldname": "preliminary_investigation_section",
   "fieldtype": "Section Break",
   "label": "Deprecated Fields"
  },
  {
   "description": "Log the findings and actions taken",
   "fieldname": "likely_cause",
   "fieldtype": "Markdown Editor",
   "label": "Likely Causes"
  },
  {
   "fieldname": "investigation",
   "fieldtype": "Link",
   "label": "Investigation",
   "options": "Incident Investigator",
   "search_index": 1
  },
  {
   "default": "0",
   "fieldname": "called_customer",
   "fieldtype": "Check",
   "label": "Called Customer"
  },
  {
   "fieldname": "resolved_at",
   "fieldtype": "Datetime",
   "label": "Resolved At"
  },
  {
   "fieldname": "confirmed_at",
   "fieldtype": "Datetime",
   "label": "Confirmed At"
  },
  {
   "fieldname": "section_break_lazo",
   "fieldtype": "Section Break"
  },
  {
   "fieldname": "column_break_ukex",
   "fieldtype": "Column Break"
  },
  {
   "fieldname": "column_break_kwec",
   "fieldtype": "Column Break"
  },
  {
   "fieldname": "column_break_xvko",
   "fieldtype": "Column Break"
  },
  {
   "fieldname": "column_break_zzcp",
   "fieldtype": "Column Break"
  },
  {
   "fieldname": "section_break_pahe",
   "fieldtype": "Section Break"
  },
  {
   "fieldname": "acknowledged_at",
   "fieldtype": "Datetime",
   "label": "Acknowledged At"
  },
  {
   "fieldname": "column_break_hryl",
   "fieldtype": "Column Break"
  },
  {
   "fieldname": "app_server_stats",
   "fieldtype": "Attach Image",
   "hidden": 1,
   "label": "App Server Stats"
  },
  {
   "fieldname": "db_server_stats",
   "fieldtype": "Attach Image",
   "hidden": 1,
   "label": "DB Server Stats"
  },
  {
   "fieldname": "app_server_stats_html",
   "fieldtype": "HTML",
   "label": "App Server Stats"
  },
  {
   "fieldname": "db_server_stats_html",
   "fieldtype": "HTML",
   "label": "DB Server Stats",
   "max_height": "512px",
   "width": "512px"
  },
  {
   "collapsible_depends_on": "eval: false",
   "fieldname": "grafana_dashboard_section",
   "fieldtype": "Section Break",
   "label": "Grafana Snapshot"
  },
  {
   "fieldname": "last_1_hour_overview_section",
   "fieldtype": "Section Break",
   "label": "Last 1 Hour P95 Overview"
  },
  {
   "fieldname": "server_oom_kills",
   "fieldtype": "Int",
   "label": "OOM Kills",
   "read_only": 1
  },
  {
   "fieldname": "column_break_iqfx",
   "fieldtype": "Column Break",
   "label": "DB Server"
  },
  {
   "fieldname": "db_server_free_memory_mb",
   "fieldtype": "Int",
   "label": "Free Memory (MB)",
   "read_only": 1
  },
  {
   "fieldname": "server_health_tab",
   "fieldtype": "Tab Break",
   "label": "Server Health"
  },
  {
   "fieldname": "app_server_column",
   "fieldtype": "Column Break",
   "label": "App Server"
  },
  {
   "fieldname": "db_server_disk_queue",
   "fieldtype": "Int",
   "label": "Disk Queue",
   "read_only": 1
  },
  {
   "fieldname": "server_status",
   "fieldtype": "Select",
   "label": "Status",
   "options": "\nReachable\nUnreachable",
   "read_only": 1
  },
  {
   "fieldname": "db_server_status",
   "fieldtype": "Select",
   "label": "Status",
   "options": "\nReachable\nUnreachable\nReachable - DB Healthy\nReachable - DB Unhealthy",
   "read_only": 1
  },
  {
   "fieldname": "analysis_tab",
   "fieldtype": "Tab Break",
   "label": "Down Resources"
  },
  {
   "fieldname": "down_sites",
   "fieldtype": "Table",
   "label": "Down Sites (Random 15)",
   "options": "Incident Site"
  },
  {
   "fieldname": "down_benches",
   "fieldtype": "Table",
   "label": "Down Benches",
   "options": "Incident Bench"
  },
  {
   "fieldname": "section_break_qefz",
   "fieldtype": "Section Break"
  },
  {
   "fieldname": "no_of_total_sites",
   "fieldtype": "Int",
   "label": "Total Sites",
   "read_only": 1
  },
  {
   "fieldname": "no_of_total_benches",
   "fieldtype": "Int",
   "label": "Total Benches",
   "read_only": 1
  },
  {
   "fieldname": "column_break_vxrf",
   "fieldtype": "Column Break"
  },
  {
   "fieldname": "no_of_down_sites",
   "fieldtype": "Int",
   "label": "Down Sites",
   "read_only": 1
  },
  {
   "fieldname": "no_of_down_benches",
   "fieldtype": "Int",
   "label": "Down Benches",
   "read_only": 1
  },
  {
   "fieldname": "server_free_space_gb",
   "fieldtype": "Float",
   "label": "Free Space (GB)",
   "read_only": 1
  },
  {
   "fieldname": "db_free_space_gb",
   "fieldtype": "Float",
   "label": "Free Space (GB)",
   "read_only": 1
  },
  {
   "fieldname": "server_load15",
   "fieldtype": "Float",
   "label": "Load 15",
   "read_only": 1
  },
  {
   "fieldname": "db_server_load15",
   "fieldtype": "Float",
   "label": "Load 15",
   "read_only": 1
  },
  {
   "fieldname": "server_runnable_state",
   "fieldtype": "Int",
   "label": "Runnable State",
   "read_only": 1
  },
  {
   "fieldname": "server_disk_iops",
   "fieldtype": "Int",
   "label": "Disk IOPS",
   "read_only": 1
  },
  {
   "fieldname": "server_disk_throughput_mbps",
   "fieldtype": "Int",
   "label": "Disk Throughput (MB/s)",
   "read_only": 1
  },
  {
   "fieldname": "db_server_disk_iops",
   "fieldtype": "Int",
   "label": "Disk IOPS",
   "read_only": 1
  },
  {
   "fieldname": "db_server_disk_throughput_mbps",
   "fieldtype": "Int",
   "label": "Disk Throughput (MB/s)",
   "read_only": 1
  },
  {
   "fieldname": "section_break_heda",
   "fieldtype": "Section Break"
  }
 ],
 "links": [],
 "modified": "2026-05-02 04:25:52.771728",
 "modified_by": "Administrator",
 "module": "Press",
 "name": "Incident",
 "owner": "Administrator",
 "permissions": [
  {
   "create": 1,
   "delete": 1,
   "email": 1,
   "export": 1,
   "print": 1,
   "read": 1,
   "report": 1,
   "role": "System Manager",
   "share": 1,
   "write": 1
  },
  {
   "email": 1,
   "export": 1,
   "print": 1,
   "read": 1,
   "report": 1,
   "role": "Press Member",
   "share": 1
  },
  {
   "email": 1,
   "export": 1,
   "print": 1,
   "read": 1,
   "report": 1,
   "role": "Press Admin",
   "share": 1
  }
 ],
 "row_format": "Dynamic",
 "rows_threshold_for_grid_search": 20,
 "sort_field": "modified",
 "sort_order": "DESC",
 "states": []
}
